jokepie/__init__.py
jokepie/__main__.py
jokepie-1.0.5.dist-info/METADATA
jokepie-1.0.5.dist-info/WHEEL
jokepie-1.0.5.dist-info/top_level.txt
jokepie-1.0.5.dist-info/RECORD
