Metadata-Version: 2.1
Name: jokepie
Version: 1.0.5
Summary: API Wrapper for sv443's joke api
Home-page: UNKNOWN
Author: TheWever (Wever#3255)
Author-email: <nonarrator@gmail.com>
License: UNKNOWN
Keywords: python,jokes,api-wrapper,api wrapper,nv443,requests
Platform: UNKNOWN
Classifier: Development Status :: 5 - Production/Stable
Classifier: Intended Audience :: Developers
Classifier: Programming Language :: Python :: 3
Classifier: Operating System :: Unix
Classifier: Operating System :: MacOS :: MacOS X
Classifier: Operating System :: Microsoft :: Windows
Requires-Dist: datetime
